mutt_wizard/__init__.py
mutt_wizard/cli.py
mutt_wizard/config.py
mutt_wizard/mailsync.py
mutt_wizard/oauth.py
mutt_wizard/templates.py
mutt_wizard-0.1.2.dist-info/METADATA
mutt_wizard-0.1.2.dist-info/WHEEL
mutt_wizard-0.1.2.dist-info/entry_points.txt
mutt_wizard-0.1.2.dist-info/top_level.txt
mutt_wizard-0.1.2.dist-info/RECORD
