Metadata-Version: 2.4
Name: mutt-wizard
Version: 0.1.2
Summary: Python starter for configuring neomutt with Gmail OAuth.
License: MIT
Requires-Python: >=3.10
Requires-Dist: google-auth>=2.29.0
Requires-Dist: google-auth-oauthlib>=1.2.0
Requires-Dist: requests>=2.31.0
